onboard/__init__.py
onboard/admin.py
onboard/apps.py
onboard/forms.py
onboard/models.py
onboard/tests.py
onboard/urls.py
onboard/views.py
onboard/migrations/0001_initial.py
onboard/migrations/0002_alter_onboarddet_employee.py
onboard/migrations/0003_topik.py
onboard/migrations/0004_alter_onboard_topic.py
onboard/migrations/__init__.py
onboard/migrations/__pycache__/0001_initial.cpython-310.pyc
onboard/migrations/__pycache__/0001_initial.cpython-37.pyc
onboard/migrations/__pycache__/0001_initial.cpython-39.pyc
onboard/migrations/__pycache__/0002_alter_onboarddet_employee.cpython-310.pyc
onboard/migrations/__pycache__/0002_alter_onboarddet_employee.cpython-37.pyc
onboard/migrations/__pycache__/0002_alter_onboarddet_employee.cpython-39.pyc
onboard/migrations/__pycache__/0003_topik.cpython-310.pyc
onboard/migrations/__pycache__/0004_alter_onboard_topic.cpython-310.pyc
onboard/migrations/__pycache__/__init__.cpython-310.pyc
onboard/migrations/__pycache__/__init__.cpython-37.pyc
onboard/migrations/__pycache__/__init__.cpython-39.pyc
onboard/templates/onboard/dash.html
onboard/templates/onboard/det_list.html
onboard/templates/onboard/emp_det_list.html
onboard/templates/onboard/emp_list.html
onboard/templates/onboard/form.html
onboard/templates/onboard/topic_list.html
onboard/views/__init__.py
onboard/views/onboard_m.py
onboard/views/onboard_v.py
onboard/views/__pycache__/__init__.cpython-310.pyc
onboard/views/__pycache__/__init__.cpython-37.pyc
onboard/views/__pycache__/__init__.cpython-39.pyc
onboard/views/__pycache__/onboard_m.cpython-310.pyc
onboard/views/__pycache__/onboard_m.cpython-37.pyc
onboard/views/__pycache__/onboard_m.cpython-39.pyc
onboard/views/__pycache__/onboard_v.cpython-310.pyc
onboard/views/__pycache__/onboard_v.cpython-37.pyc
onboard/views/__pycache__/onboard_v.cpython-39.pyc
django_ipghrms_onboarding-1.1.dist-info/LICENSE
django_ipghrms_onboarding-1.1.dist-info/METADATA
django_ipghrms_onboarding-1.1.dist-info/WHEEL
django_ipghrms_onboarding-1.1.dist-info/top_level.txt
django_ipghrms_onboarding-1.1.dist-info/RECORD
